Metadata-Version: 1.1
Name: ftw.crawler
Version: 1.2.1
Summary: Crawl sites, extract text and metadata, index it in Solr
Home-page: https://github.com/4teamwork/ftw.crawler
Author: 4teamwork AG
Author-email: mailto:info@4teamwork.ch
License: GPL2
Keywords: crawling extraction solr
Platform: UNKNOWN
Classifier: Intended Audience :: Developers
Classifier: License :: OSI Approved :: GNU General Public License (GPL)
Classifier: Programming Language :: Python
Classifier: Topic :: Software Development
